onomaspy/__init__.py
onomaspy/klass.py
onomaspy/listy.py
onomaspy/main.py
onomaspy/name.py
onomaspy/name_divider.py
onomaspy/personal_name.py
onomaspy/registry.py
onomaspy-0.0.2.dist-info/AUTHORS.rst
onomaspy-0.0.2.dist-info/LICENSE.txt
onomaspy-0.0.2.dist-info/METADATA
onomaspy-0.0.2.dist-info/WHEEL
onomaspy-0.0.2.dist-info/entry_points.txt
onomaspy-0.0.2.dist-info/top_level.txt
onomaspy-0.0.2.dist-info/RECORD
