Metadata-Version: 2.1
Name: onomaspy
Version: 0.0.2
Summary: Deterministic classifier for personal names
Home-page: https://github.com/flbulgarelli/onomaspy
Author: Franco Bulgarelli
Author-email: franco@mumuki.org
License: gpl3
Project-URL: Documentation, https://github.com/flbulgarelli/onomaspy
Project-URL: Bug Tracker, https://github.com/flbulgarelli/onomaspy/issues
Platform: any
Classifier: Programming Language :: Python :: 3
License-File: LICENSE.txt
License-File: AUTHORS.rst
Requires-Dist: importlib-metadata
Requires-Dist: Unidecode (~=1.1)
Provides-Extra: testing
Requires-Dist: setuptools ; extra == 'testing'
Requires-Dist: pytest ; extra == 'testing'
Requires-Dist: pytest-cov ; extra == 'testing'
